pywarsaw/__init__.py
pywarsaw/client.py
pywarsaw/exceptions.py
pywarsaw/objects.py
pywarsaw/pywarsaw.py
pywarsaw/utils.py
pywarsaw-0.1.1.dist-info/LICENSE
pywarsaw-0.1.1.dist-info/WHEEL
pywarsaw-0.1.1.dist-info/METADATA
pywarsaw-0.1.1.dist-info/RECORD
