Metadata-Version: 2.1
Name: pywarsaw
Version: 0.1.1
Summary: An unofficial asynchronous API wrapper for Warsaw Open Data - https://api.um.warszawa.pl/
Home-page: https://github.com/BrozenSenpai/pywarsaw
License: MIT
Keywords: Warsaw
Author: brozen
Author-email: szymon.mazurkievicz@gmail.com
Requires-Python: >=3.9,<4.0
Classifier: License :: OSI Approved :: MIT License
Classifier: Programming Language :: Python :: 3
Classifier: Programming Language :: Python :: 3.10
Classifier: Programming Language :: Python :: 3.9
Requires-Dist: aiohttp (>=3.8.3,<4.0.0)
Requires-Dist: aiohttp-client-cache (>=0.8.1,<0.9.0)
Requires-Dist: aiosqlite (>=0.18.0,<0.19.0)
Requires-Dist: attrs (>=22.2.0,<23.0.0)
Project-URL: Documentation, https://pywarsaw.readthedocs.io/en/latest/
